{
    "bundle" : "websockets",
    "dependencies" : [ "jquery" ],
    "assets": [
        {
            "name": "socket.io",
            "version": "1.0.0",
            "type": "js",
            "locations": {
                "classpath": "static/assets/socket.io.js"
            }
        },
        {
            "name": "sockjs",
            "version": "0.3.4",
            "type": "js",
            "locations": {
                "classpath": "static/assets/sockjs-0.3.4.js"
            }
        }
    ]
}
